{
  "vocab_size": 14581,
  "total_bpe_tokens": 1597426672,
  "num_merged_tokens": 8192,
  "average_bpe_token_length": 2.1255,
  "most_common_bpe_tokens": [
    {
      "original_tokens": "<velocity-80>",
      "corpus_count": 7212240
    },
    {
      "original_tokens": "<velocity-90>",
      "corpus_count": 7130471
    },
    {
      "original_tokens": "<velocity-110>",
      "corpus_count": 6855521
    },
    {
      "original_tokens": "<velocity-64>",
      "corpus_count": 6701342
    },
    {
      "original_tokens": "<time-5000> <duration-10>",
      "corpus_count": 5879447
    },
    {
      "original_tokens": "<velocity-96>",
      "corpus_count": 5746108
    },
    {
      "original_tokens": "<velocity-85>",
      "corpus_count": 5644971
    },
    {
      "original_tokens": "<velocity-70>",
      "corpus_count": 5623240
    },
    {
      "original_tokens": "<velocity-95>",
      "corpus_count": 5609007
    },
    {
      "original_tokens": "<time-5000> <duration-12>",
      "corpus_count": 5603755
    }
  ],
  "most_common_categories": [
    {
      "category": "instrument",
      "merged_vocab_count": 6991,
      "corpus_weighted_count": 519460488
    },
    {
      "category": "pitch",
      "merged_vocab_count": 7352,
      "corpus_weighted_count": 510295798
    },
    {
      "category": "duration",
      "merged_vocab_count": 3520,
      "corpus_weighted_count": 394397061
    },
    {
      "category": "time",
      "merged_vocab_count": 2443,
      "corpus_weighted_count": 334096881
    },
    {
      "category": "velocity",
      "merged_vocab_count": 4293,
      "corpus_weighted_count": 191344679
    }
  ],
  "component_analysis": {
    "2": [
      {
        "categories": "instrument+pitch",
        "vocab_count": 1758,
        "corpus_count": 237977509
      },
      {
        "categories": "duration+time",
        "vocab_count": 392,
        "corpus_count": 220789477
      },
      {
        "categories": "instrument+velocity",
        "vocab_count": 448,
        "corpus_count": 37914009
      },
      {
        "categories": "duration+pitch",
        "vocab_count": 252,
        "corpus_count": 7462334
      }
    ],
    "3": [
      {
        "categories": "instrument+pitch+velocity",
        "vocab_count": 2466,
        "corpus_count": 98710705
      },
      {
        "categories": "duration+instrument+pitch",
        "vocab_count": 351,
        "corpus_count": 34744889
      },
      {
        "categories": "duration+pitch+time",
        "vocab_count": 557,
        "corpus_count": 21286985
      }
    ],
    "4": [
      {
        "categories": "duration+instrument+pitch+time",
        "vocab_count": 589,
        "corpus_count": 55393411
      },
      {
        "categories": "duration+instrument+pitch+velocity",
        "vocab_count": 474,
        "corpus_count": 18092957
      }
    ],
    "5": [
      {
        "categories": "duration+instrument+pitch+time+velocity",
        "vocab_count": 905,
        "corpus_count": 36627008
      }
    ]
  }
}